openttd_protocol/__init__.py
openttd_protocol/protocol/__init__.py
openttd_protocol/protocol/content.py
openttd_protocol/protocol/coordinator.py
openttd_protocol/protocol/game.py
openttd_protocol/protocol/stun.py
openttd_protocol/protocol/turn.py
openttd_protocol/wire/__init__.py
openttd_protocol/wire/exceptions.py
openttd_protocol/wire/read.py
openttd_protocol/wire/source.py
openttd_protocol/wire/tcp.py
openttd_protocol/wire/test_read.py
openttd_protocol/wire/test_tcp.py
openttd_protocol/wire/test_write.py
openttd_protocol/wire/write.py
openttd_protocol-1.7.1.dist-info/LICENSE
openttd_protocol-1.7.1.dist-info/METADATA
openttd_protocol-1.7.1.dist-info/WHEEL
openttd_protocol-1.7.1.dist-info/top_level.txt
openttd_protocol-1.7.1.dist-info/RECORD
