Metadata-Version: 2.1
Name: openttd-protocol
Version: 1.7.1
Summary: OpenTTD network protocol for Python
Home-page: https://github.com/OpenTTD/py-protocol
Author: OpenTTD Dev Team
Author-email: info@openttd.org
License: UNKNOWN
Platform: UNKNOWN
Classifier: Programming Language :: Python :: 3
Classifier: License :: OSI Approved :: GNU Lesser General Public License v2 (LGPLv2)
Classifier: Operating System :: OS Independent
Requires-Python: >=3.8
